shelf_audit_preprocess/__init__.py
shelf_audit_preprocess/augmentation.py
shelf_audit_preprocess/data_extraction.py
shelf_audit_preprocess/split_data.py
shelf_audit_preprocess-1.0.15.dist-info/METADATA
shelf_audit_preprocess-1.0.15.dist-info/WHEEL
shelf_audit_preprocess-1.0.15.dist-info/top_level.txt
shelf_audit_preprocess-1.0.15.dist-info/RECORD
