Metadata-Version: 2.1
Name: shelf_audit_preprocess
Version: 1.0.15
Summary: Pre processing for model training.
Author: Blackstraw
Author-email: arshpreet.singh@blackstraw.ai
Classifier: Programming Language :: Python :: 3
Classifier: License :: OSI Approved :: MIT License
Classifier: Operating System :: OS Independent
Requires-Python: >=3.8
Requires-Dist: albumentations ==1.4.11
Requires-Dist: matplotlib
Requires-Dist: numpy
Requires-Dist: opencv-python ==4.10.0.84
Requires-Dist: opencv-python-headless ==4.10.0.84
Requires-Dist: tqdm ==4.66.4
